pdp/__init__.py
pdp/mediator/__init__.py
pdp/mediator/base_component.py
pdp/mediator/mediator.py
pdp/memento/__init__.py
pdp/memento/base_originator.py
pdp/memento/caretaker.py
pdp/memento/memento.py
pdp/pipeline/__init__.py
pdp/pipeline/pipeline.py
pdp/pipeline/pipeline_error.py
pdp/pipeline/step.py
python_design_patterns-0.2.1.dist-info/METADATA
python_design_patterns-0.2.1.dist-info/WHEEL
python_design_patterns-0.2.1.dist-info/entry_points.txt
python_design_patterns-0.2.1.dist-info/RECORD
