Metadata-Version: 2.1
Name: python-design-patterns
Version: 0.2.1
Summary: A Python library for implementing design patterns
License: MIT
Author: Vodkas
Author-email: vodkas3630@gmail.com
Requires-Python: >=3.9,<4.0
Classifier: License :: OSI Approved :: MIT License
Classifier: Programming Language :: Python :: 3
Classifier: Programming Language :: Python :: 3.9
Classifier: Programming Language :: Python :: 3.10
Classifier: Programming Language :: Python :: 3.11
Classifier: Programming Language :: Python :: 3.12
Classifier: Programming Language :: Python :: 3.13
